langsrc/__init__.py
langsrc-0.0.9.dist-info/METADATA
langsrc-0.0.9.dist-info/WHEEL
langsrc-0.0.9.dist-info/RECORD
